entrypoint.py
lodgify_server.py
mcp.json
lodgify_mcp_server-0.2.2.dist-info/METADATA
lodgify_mcp_server-0.2.2.dist-info/WHEEL
lodgify_mcp_server-0.2.2.dist-info/entry_points.txt
lodgify_mcp_server-0.2.2.dist-info/licenses/LICENSE
lodgify_mcp_server-0.2.2.dist-info/RECORD
