Metadata-Version: 2.4
Name: lodgify-mcp-server
Version: 0.2.2
Summary: A Model Context Protocol server for interacting with the Lodgify vacation rental API
Project-URL: Homepage, https://github.com/fast-transients/lodgify-mcp-server
Project-URL: Repository, https://github.com/fast-transients/lodgify-mcp-server
Project-URL: Issues, https://github.com/fast-transients/lodgify-mcp-server/issues
Author-email: Shane <shane@shanephall.com>
License-File: LICENSE
Keywords: api,lodgify,mcp,model-context-protocol,vacation-rental
Classifier: Development Status :: 4 - Beta
Classifier: Intended Audience :: Developers
Classifier: License :: OSI Approved :: MIT License
Classifier: Programming Language :: Python :: 3
Classifier: Programming Language :: Python :: 3.10
Classifier: Programming Language :: Python :: 3.11
Classifier: Programming Language :: Python :: 3.12
Requires-Python: >=3.10
Requires-Dist: httpx>=0.28.1
Requires-Dist: mcp[cli]>=1.9.1
Provides-Extra: dev
Requires-Dist: mypy>=1.0.0; extra == 'dev'
Requires-Dist: pytest-asyncio>=0.21.0; extra == 'dev'
Requires-Dist: pytest-cov>=4.0.0; extra == 'dev'
Requires-Dist: pytest-httpx>=0.30.0; extra == 'dev'
Requires-Dist: pytest-mock>=3.10.0; extra == 'dev'
Requires-Dist: pytest>=7.0.0; extra == 'dev'
Requires-Dist: ruff>=0.1.0; extra == 'dev'
